simcx/__init__.py
simcx/__version__.py
simcx/simulators.py
simcx/visuals.py
simcx-1.0.0b22.dist-info/LICENSE.txt
simcx-1.0.0b22.dist-info/METADATA
simcx-1.0.0b22.dist-info/WHEEL
simcx-1.0.0b22.dist-info/top_level.txt
simcx-1.0.0b22.dist-info/RECORD
