Metadata-Version: 2.1
Name: simcx
Version: 1.0.0b22
Summary: Simulation Framework for Complex Systems
Home-page: https://github.com/tbaptista/simcx
Author: Tiago Baptista
Author-email: baptista@dei.uc.pt
License: Apache License 2.0
Classifier: Development Status :: 4 - Beta
Classifier: Intended Audience :: Education
Classifier: Intended Audience :: Science/Research
Classifier: License :: OSI Approved :: Apache Software License
Classifier: Natural Language :: English
Classifier: Operating System :: OS Independent
Classifier: Programming Language :: Python :: 3
Classifier: Programming Language :: Python :: 2.7
Classifier: Topic :: Education
Classifier: Topic :: Scientific/Engineering
Classifier: Topic :: Scientific/Engineering :: Artificial Intelligence
Classifier: Topic :: Scientific/Engineering :: Artificial Life
License-File: LICENSE.txt
Requires-Dist: pyglet
Requires-Dist: matplotlib
Requires-Dist: numpy
Requires-Dist: scipy
Requires-Dist: pyafai
